collective.impersonate-2.0-py3.11-nspkg.pth
collective/impersonate/__init__.py
collective/impersonate/configure.zcml
collective/impersonate/interfaces.py
collective/impersonate/setuphandlers.py
collective/impersonate/testing.py
collective/impersonate/browser/__init__.py
collective/impersonate/browser/configure.zcml
collective/impersonate/browser/impersonate.pt
collective/impersonate/browser/impersonate.py
collective/impersonate/browser/overrides/.gitkeep
collective/impersonate/browser/static/.gitkeep
collective/impersonate/locales/collective.impersonate.pot
collective/impersonate/locales/plone.pot
collective/impersonate/locales/update.sh
collective/impersonate/locales/fr/LC_MESSAGES/collective.impersonate.po
collective/impersonate/locales/fr/LC_MESSAGES/plone.po
collective/impersonate/profiles/default/actions.xml
collective/impersonate/profiles/default/browserlayer.xml
collective/impersonate/profiles/default/metadata.xml
collective/impersonate/profiles/default/registry.xml
collective/impersonate/profiles/uninstall/actions.xml
collective/impersonate/profiles/uninstall/browserlayer.xml
collective/impersonate/profiles/upgrades/to_1100/actions.xml
collective/impersonate/tests/__init__.py
collective/impersonate/tests/test_setup.py
collective.impersonate-2.0.dist-info/METADATA
collective.impersonate-2.0.dist-info/WHEEL
collective.impersonate-2.0.dist-info/entry_points.txt
collective.impersonate-2.0.dist-info/namespace_packages.txt
collective.impersonate-2.0.dist-info/top_level.txt
collective.impersonate-2.0.dist-info/RECORD
