Metadata-Version: 2.1
Name: collective.impersonate
Version: 2.0
Summary: Allow administrator to impersonate another user, for debugging purposes.
Home-page: https://github.com/collective/collective.impersonate
Author: NiteoWeb Ltd.
Author-email: info@niteoweb.com
License: GPL version 2
Keywords: Python Plone
Classifier: Development Status :: 5 - Production/Stable
Classifier: Environment :: Web Environment
Classifier: Framework :: Plone
Classifier: Framework :: Plone :: Addon
Classifier: Framework :: Plone :: 6.0
Classifier: Programming Language :: Python
Classifier: Programming Language :: Python :: 3.8
Classifier: Programming Language :: Python :: 3.9
Classifier: Programming Language :: Python :: 3.10
Classifier: Programming Language :: Python :: 3.11
Classifier: Operating System :: OS Independent
Classifier: License :: OSI Approved :: GNU General Public License v2 (GPLv2)
Requires-Python: >=3.8
Requires-Dist: plone.api
Requires-Dist: setuptools
Requires-Dist: z3c.jbot
Requires-Dist: Products.GenericSetup
Provides-Extra: test
Requires-Dist: plone.app.testing; extra == "test"
